allantools/__init__.py
allantools/allantools.py
allantools/allantools_info.json
allantools/ci.py
allantools/dataset.py
allantools/mask.py
allantools/noise.py
allantools/noise_kasdin.py
allantools/plot.py
allantools/realtime.py
AllanTools-2024.4.dist-info/LICENSE.txt
AllanTools-2024.4.dist-info/METADATA
AllanTools-2024.4.dist-info/WHEEL
AllanTools-2024.4.dist-info/top_level.txt
AllanTools-2024.4.dist-info/RECORD
