Metadata-Version: 2.1
Name: AllanTools
Version: 2024.4
Summary: Allan deviation and related time/frequency statistics
Home-page: https://github.com/aewallin/allantools
Author: Anders E. E. Wallin
Author-email: anders.e.e.wallin@gmail.com
License: LGPLv3+
Requires: numpy
Requires: scipy
License-File: LICENSE.txt
Requires-Dist: numpy
Requires-Dist: scipy
